json_stream_reader/__init__.py
json_stream_reader/cli.py
json_stream_reader/json_stream_reader.py
json_stream_reader-0.2.0.dist-info/AUTHORS.rst
json_stream_reader-0.2.0.dist-info/LICENSE
json_stream_reader-0.2.0.dist-info/METADATA
json_stream_reader-0.2.0.dist-info/WHEEL
json_stream_reader-0.2.0.dist-info/entry_points.txt
json_stream_reader-0.2.0.dist-info/top_level.txt
json_stream_reader-0.2.0.dist-info/RECORD
