Metadata-Version: 2.1
Name: json-stream-reader
Version: 0.2.0
Summary: Given a byte stream of {}-bracketed objects, generate one object-string at a time.
Home-page: https://github.com/matt2000/json_stream_reader
Author: Matt Chapman
Author-email: matt@ninjitsuweb.com
License: GNU General Public License v3
Keywords: json_stream_reader
Platform: UNKNOWN
Classifier: Development Status :: 2 - Pre-Alpha
Classifier: Intended Audience :: Developers
Classifier: License :: OSI Approved :: GNU General Public License v3 (GPLv3)
Classifier: Natural Language :: English
Classifier: Programming Language :: Python :: 3
Classifier: Programming Language :: Python :: 3.4
Classifier: Programming Language :: Python :: 3.5
Classifier: Programming Language :: Python :: 3.6
Classifier: Programming Language :: Python :: 3.7
Requires-Dist: Click (>=6.0)
Requires-Dist: mypy
